iden3math-0.1.2.dist-info/RECORD
iden3math-0.1.2.dist-info/WHEEL
iden3math-0.1.2.dist-info/METADATA
iden3math-0.1.2.dist-info/licenses/LICENSE
iden3math/random.pyi
iden3math/__init__.pyi
iden3math/typedef.pyi
iden3math/__init__.py
iden3math/iden3math.cpython-313-darwin.so
iden3math/fp1.pyi
iden3math/prime.pyi
iden3math/bitvec.pyi
iden3math/hash/mimc.pyi
iden3math/hash/__init__.pyi
iden3math/hash/keccak.pyi
iden3math/hash/blake.pyi
iden3math/hash/pedersen.pyi
iden3math/ec/__init__.pyi
iden3math/ec/babyjub.pyi
iden3math/ec/point.pyi
