Metadata-Version: 2.2
Name: iden3math
Version: 0.1.2
License:                     GNU GENERAL PUBLIC LICENSE
Requires-Python: <3.14,>=3.8
